games/__init__.py
games/maze.py
py_maze_maker-0.0.1.data/scripts/maze-maker
py_maze_maker-0.0.1.dist-info/LICENSE.txt
py_maze_maker-0.0.1.dist-info/METADATA
py_maze_maker-0.0.1.dist-info/WHEEL
py_maze_maker-0.0.1.dist-info/top_level.txt
py_maze_maker-0.0.1.dist-info/RECORD
