Metadata-Version: 2.1
Name: py-maze-maker
Version: 0.0.1
Summary: A simple Python package to make ASCII maze.
Home-page: https://github.com/manwar/py-maze-maker
Author: Mohammad Sajid Anwar
Author-email: mohammad.anwar@yahoo.com
License: UNKNOWN
Project-URL: Bug Tracker, https://github.com/manwar/py-maze-maker/issues
Project-URL: repository, https://github.com/manwar/py-maze-maker
Platform: UNKNOWN
Classifier: Programming Language :: Python :: 3
Classifier: License :: OSI Approved :: MIT License
Classifier: Operating System :: OS Independent
Requires-Python: >=3.6
